addressformatting/__init__.py
addressformatting/format.py
addressformatting/py.typed
addressformatting/util.py
addressformatting/data/worldwide.yml
addressformatting-1.3.2.dist-info/LICENSE.txt
addressformatting-1.3.2.dist-info/METADATA
addressformatting-1.3.2.dist-info/WHEEL
addressformatting-1.3.2.dist-info/top_level.txt
addressformatting-1.3.2.dist-info/RECORD
