Metadata-Version: 2.1
Name: addressformatting
Version: 1.3.2
Summary: Formatting utility for international postal addresses
Home-page: https://github.com/pudo/addressformatting
Author: Friedrich Lindenberg
Author-email: friedrich@pudo.org
License: BSD
Keywords: address formatting,international
Classifier: Development Status :: 5 - Production/Stable
Classifier: Intended Audience :: Developers
Classifier: License :: OSI Approved :: BSD License
Classifier: Programming Language :: Python
Classifier: Programming Language :: Python :: 3
Classifier: Programming Language :: Python :: 3.9
Classifier: Operating System :: OS Independent
License-File: LICENSE.txt
Requires-Dist: PyYAML (>=5.0)
Requires-Dist: chevron (>=0.14.0)
Provides-Extra: dev
Requires-Dist: pytest ; extra == 'dev'
Requires-Dist: bump2version ; extra == 'dev'
Requires-Dist: wheel (>=0.29.0) ; extra == 'dev'
Requires-Dist: twine ; extra == 'dev'
